jableparser/__init__.py
jableparser/model.py
jableparser/region.py
jableparser/tags_util.py
jableparser-0.0.1.dist-info/DESCRIPTION.rst
jableparser-0.0.1.dist-info/METADATA
jableparser-0.0.1.dist-info/RECORD
jableparser-0.0.1.dist-info/WHEEL
jableparser-0.0.1.dist-info/metadata.json
jableparser-0.0.1.dist-info/top_level.txt
