Metadata-Version: 2.0
Name: jableparser
Version: 0.0.1
Summary: A enhanced parser which can extract title, content, images and form from html pages, inspired by jparser
Home-page: https://github.com/qjfoidnh/jableparser
Author: qjfoidnh
Author-email: qjfoidnh@126.com
License: MIT
Platform: UNKNOWN
Requires-Dist: Beautifulsoup4 (>=4.2.0)
Requires-Dist: lxml (>=3.7.1)
